Metadata-Version: 2.1
Name: odoo14-addon-shopinvader_locomotive_algolia
Version: 14.0.1.0.1.dev4
Summary: This addons is used to push the initial algolia configuration to locomotive
Home-page: https://github.com/shopinvader/odoo-shopinvader
Author: Camptcamp SA
License: AGPL-3
Classifier: Programming Language :: Python
Classifier: Framework :: Odoo
Classifier: Framework :: Odoo :: 14.0
Classifier: License :: OSI Approved :: GNU Affero General Public License v3
Requires-Python: >=3.6
Requires-Dist: odoo14-addon-component
Requires-Dist: odoo14-addon-shopinvader-algolia
Requires-Dist: odoo14-addon-shopinvader-locomotive
Requires-Dist: odoo <14.1dev,>=14.0a
